xlmtools/__init__.py
xlmtools/bibtex.py
xlmtools/constants.py
xlmtools/xlmtools_logo.jpg
xlmtools/protocols/__init__.py
xlmtools/protocols/protocol_wlm.py
xlmtools/testdata/gs.pdb
xlmtools/tests/__init__.py
xlmtools/tests/test_protocols_xlm.py
xlmtools/viewers/__init__.py
xlmtools/viewers/viewer_xlm.py
scipion_em_xlmtools-1.0.0.dist-info/LICENSE
scipion_em_xlmtools-1.0.0.dist-info/METADATA
scipion_em_xlmtools-1.0.0.dist-info/WHEEL
scipion_em_xlmtools-1.0.0.dist-info/entry_points.txt
scipion_em_xlmtools-1.0.0.dist-info/top_level.txt
scipion_em_xlmtools-1.0.0.dist-info/RECORD
